[
    {
        "id": 1,
        "name": "Casa de Playa",
        "place": "La Pedrera, Uruguay",
        "type": "Project",
        "description": "Description of Project A",
        "date": "2023-01-01",
        "isHomepage": true,
        "homeThumb": "https://placehold.co/600x400/FFFFFF/A89A90?text=Imagen+No+Disponible"
    },
    {
        "id": 2,
        "name": "Departamento Nordelta",
        "place": "Tigre, Argentina",
        "type": "Project",
        "description": "Description of Project B",
        "date": "2023-01-01",
        "isHomepage": true,
        "homeThumb": "https://placehold.co/600x400/FFFFFF/A89A90?text=Imagen+No+Disponible"
    },
    {
        "id": 3,
        "name": "Comedor Vitacura",
        "place": "Santiago, Chile",
        "type": "Project",
        "description": "Description of Project C",
        "date": "2023-01-01",
        "isHomepage": true,
        "homeThumb": "https://placehold.co/600x400/FFFFFF/A89A90?text=Imagen+No+Disponible"
    },
    {
        "id": 4,
        "name": "Mesas de Comedor",
        "place": "Ideas Variadas",
        "type": "Idea",
        "description": "Description of Idea A",
        "date": "2023-01-01",
        "isHomepage": true,
        "homeThumb": "../imagenes/IMG_4022_thumb.jpg"
    },
    {
        "id": 5,
        "name": "Idea B",
        "place": "Ideas Variadas",
        "type": "Idea",
        "description": "Description of Idea B",
        "date": "2023-01-01",
        "isHomepage": true,
        "homeThumb": "https://placehold.co/600x400/FFFFFF/A89A90?text=Imagen+No+Disponible"
    },
    {
        "id": 6,
        "name": "Idea C",
        "place": "Ideas Variadas",
        "type": "Idea",
        "description": "Description of Idea C",
        "date": "2023-01-01",
        "isHomepage": true,
        "homeThumb": "https://placehold.co/600x400/FFFFFF/A89A90?text=Imagen+No+Disponible"
    },
    {
        "id": 7,
        "name": "Experiencia Rural",
        "type": "El Maule, Chile",
        "description": "Description of Lugar A",
        "date": "2023-01-01",
        "isHomepage": true,
        "homeThumb": "https://placehold.co/600x400/FFFFFF/A89A90?text=Imagen+No+Disponible"
    },
    {
        "id": 8,
        "name": "Algodón Wine State",
        "type": "San Rafael, Mendoza",
        "description": "Description of Lugar B",
        "date": "2023-01-01",
        "isHomepage": true,
        "homeThumb": "https://placehold.co/600x400/FFFFFF/A89A90?text=Imagen+No+Disponible"
    },
    {
        "id": 9,
        "name": "El Norte",
        "type": "Antofagasta, Chile",
        "description": "Description of Lugar C",
        "date": "2023-01-01",
        "isHomepage": true,
        "homeThumb": "https://placehold.co/600x400/FFFFFF/A89A90?text=Imagen+No+Disponible"
    }
]